trill/__init.py__
trill/commands/__init__.py
trill/commands/classify.py
trill/commands/commands_common.py
trill/commands/diff_gen.py
trill/commands/dock.py
trill/commands/embed.py
trill/commands/finetune.py
trill/commands/fold.py
trill/commands/inv_fold_gen.py
trill/commands/lang_gen.py
trill/commands/regress.py
trill/commands/score.py
trill/commands/simulate.py
trill/commands/utils.py
trill/commands/visualize.py
trill/commands/workflow.py
trill/data/4ih9.pdb
trill/data/boltz_example_input.fasta
trill/data/chai_example_input.fasta
trill/data/cpp_ex.fasta
trill/data/if1_target.csv
trill/data/query.fasta
trill/data/target_4ih9.fa
trill/data/target_base_ProtGPT2.fasta
trill/data/target_cpp_ex.pdb
trill/data/target_esm2_t12_35M_UR50D.csv
trill/data/target_esm2_t30_150M_UR50D_Gibbs.fasta
trill/data/tuner.fasta
trill/data/vp1s.npy
trill/trill_main.py
trill/tutorial_slurm.sh
trill/utils/MLP.py
trill/utils/WranglingData.py
trill/utils/__init__.py
trill/utils/catapro.py
trill/utils/catpred.py
trill/utils/classify_utils.py
trill/utils/cuda_utils.py
trill/utils/dock_utils.py
trill/utils/ephod_utils.py
trill/utils/esm_utils.py
trill/utils/fasta_files.py
trill/utils/fetch_dbs.py
trill/utils/fetch_embs.py
trill/utils/foldseek_utils.py
trill/utils/foldtuning.py
trill/utils/genie2.py
trill/utils/inverse_folding/__init__.py
trill/utils/inverse_folding/features.py
trill/utils/inverse_folding/gvp_encoder.py
trill/utils/inverse_folding/gvp_modules.py
trill/utils/inverse_folding/gvp_transformer.py
trill/utils/inverse_folding/gvp_transformer_encoder.py
trill/utils/inverse_folding/gvp_utils.py
trill/utils/inverse_folding/multichain_util.py
trill/utils/inverse_folding/transformer_decoder.py
trill/utils/inverse_folding/transformer_layer.py
trill/utils/inverse_folding/util.py
trill/utils/lightning_models.py
trill/utils/logging.py
trill/utils/mask.py
trill/utils/materials_utils.py
trill/utils/mionic_utils.py
trill/utils/mmelon_utils.py
trill/utils/molt5_utils.py
trill/utils/poolparti.py
trill_proteins-1.9.0.dist-info/LICENSE
trill_proteins-1.9.0.dist-info/METADATA
trill_proteins-1.9.0.dist-info/WHEEL
trill_proteins-1.9.0.dist-info/entry_points.txt
trill_proteins-1.9.0.dist-info/RECORD
