Metadata-Version: 2.1
Name: trill-proteins
Version: 1.9.0
Summary: Sandbox for Computational Protein Design
Home-page: https://github.com/martinez-zacharya/TRILL
License: MIT
Keywords: NLP,Natural Language Processing,Protein Design,ESM2,ESMFold,ProteinMPNN,ProtGPT2,ZymCTRL,RFDiffusion
Author: Zachary Martinez
Author-email: martinez.zacharya@gmail.com
Requires-Python: >=3.11,<3.12
Classifier: License :: OSI Approved :: MIT License
Classifier: Programming Language :: Python :: 3
Classifier: Programming Language :: Python :: 3.11
Requires-Dist: GitPython (>=3.1.29,<4.0.0)
Requires-Dist: MDAnalysis (>=2.9.0,<3.0.0)
Requires-Dist: OpenMM (>=8.3.0,<9.0.0)
Requires-Dist: SentencePiece (>=0.1.97,<0.2.0)
Requires-Dist: accelerate (>=1.8.1,<2.0.0)
Requires-Dist: antipickle (>=0.2.0,<0.3.0)
Requires-Dist: ase (==3.24.0)
Requires-Dist: beartype (>=0.18.0,<0.19.0)
Requires-Dist: biobb_vs (>=4.1.1,<5.0.0)
Requires-Dist: biopython (==1.81)
Requires-Dist: biotite (>=0.39.0,<0.40.0)
Requires-Dist: bokeh (>=3.0.3,<4.0.0)
Requires-Dist: chardet (>=5.1.0,<6.0.0)
Requires-Dist: chembl_structure_pipeline (==1.2.2)
Requires-Dist: click (>=8.1.7,<9.0.0)
Requires-Dist: cuequivariance_ops_cu12 (>=0.5.0,<0.6.0)
Requires-Dist: cuequivariance_ops_torch_cu12 (>=0.5.0,<0.6.0)
Requires-Dist: cuequivariance_torch (>=0.5.0,<0.6.0)
Requires-Dist: datasets (>=2.7.1,<3.0.0)
Requires-Dist: deepspeed (>=0.17.1,<0.18.0)
Requires-Dist: dm-tree (>=0.1.8,<0.2.0)
Requires-Dist: e3nn (>=0.5.1,<0.6.0)
Requires-Dist: evaluate (>=0.4.2,<0.5.0)
Requires-Dist: fair-esm (>=2.0.0,<3.0.0)
Requires-Dist: fairscale (>=0.4.13,<0.5.0)
Requires-Dist: fuse-med-ml (==0.3.0)
Requires-Dist: gemmi (>=0.6.3,<0.7.0)
Requires-Dist: h5py (>=3.10.0,<4.0.0)
Requires-Dist: hydra-core (>=1.3.2,<2.0.0)
Requires-Dist: icecream (>=2.1.3,<3.0.0)
Requires-Dist: ipdb (==0.13.13)
Requires-Dist: jaxtyping (>=0.2.25,<0.3.0)
Requires-Dist: lifelines (==0.30.0)
Requires-Dist: lightgbm (>=4.4.0,<5.0.0)
Requires-Dist: llvmlite (>=0.41.0,<0.42.0)
Requires-Dist: loguru (>=0.7.2,<0.8.0)
Requires-Dist: mashumaro (>=3.14,<4.0)
Requires-Dist: matplotlib (>=3.10.3,<4.0.0)
Requires-Dist: meeko (>=0.5.1,<0.6.0)
Requires-Dist: ml-collections (>=0.1.1,<0.2.0)
Requires-Dist: modelcif (>=1.2,<2.0)
Requires-Dist: numba (>=0.58.1,<0.59.0)
Requires-Dist: numpy (>=1.26.3,<2.0.0)
Requires-Dist: omegaconf (>=2.3.0,<3.0.0)
Requires-Dist: optuna (==4.2.0)
Requires-Dist: pandas (>=2.3.0,<3.0.0)
Requires-Dist: pandera (>=0.22.1,<0.23.0)
Requires-Dist: plotly (>=6.1.2,<7.0.0)
Requires-Dist: pydantic (>=2.11.5,<3.0.0)
Requires-Dist: pyfiglet (>=0.8.post1,<0.9)
Requires-Dist: pytest (>=8.2.0,<9.0.0)
Requires-Dist: pytorch-lightning (>=2.5.1.post0,<3.0.0)
Requires-Dist: rdkit (>=2024.3.2,<2025.0.0)
Requires-Dist: reprint (>=0.6.0,<0.7.0)
Requires-Dist: scikit-learn (==1.4.1.post1)
Requires-Dist: scikit-optimize (>=0.9.0,<0.10.0)
Requires-Dist: seaborn (>=0.13.2,<0.14.0)
Requires-Dist: selfies (==2.2.0)
Requires-Dist: setuptools (==78.1.1)
Requires-Dist: skops (>=0.9.0,<0.10.0)
Requires-Dist: spyrmsd (>=0.5.2,<0.6.0)
Requires-Dist: swig (>=4.3.1,<5.0.0)
Requires-Dist: tensorboard (>=2.19.0,<3.0.0)
Requires-Dist: tensorboardx (==2.6.4)
Requires-Dist: torch-nl (==0.3)
Requires-Dist: transformers (>=4.25.1,<5.0.0)
Requires-Dist: typed-argument-parser (==1.10.1)
Requires-Dist: umap-learn (>=0.5.3,<0.6.0)
Requires-Dist: urllib3 (==1.26.18)
Requires-Dist: xgboost (>=1.7.5,<2.0.0)
Project-URL: Documentation, https://trill.readthedocs.io/en/latest/home.html
Project-URL: Repository, https://github.com/martinez-zacharya/TRILL
